lifecycle_ml_example/__init__.py
lifecycle_ml_example/artifacts/model.pkl
lifecycle_ml_example/conf/config.yaml
lifecycle_ml_example/raw_data/in-vehicle-coupon-recommendation.csv
lifecycle_ml_example/src/README.md
lifecycle_ml_example/src/data/__init__.py
lifecycle_ml_example/src/data/data_manager.py
lifecycle_ml_example/src/features/data_preprocessing.py
lifecycle_ml_example/src/main.py
lifecycle_ml_example/src/metrics/evaluate_model.py
lifecycle_ml_example/src/models/inference.py
lifecycle_ml_example/src/models/training.py
lifecycle_ml_example/src/utils/__init__.py
lifecycle_ml_example/src/utils/config.py
lifecycle_ml_example/src/utils/f_gcs_storage.py
lifecycle_ml_example/src/utils/logger_class.py
lifecycle_ml_example-0.1.0.dist-info/METADATA
lifecycle_ml_example-0.1.0.dist-info/WHEEL
lifecycle_ml_example-0.1.0.dist-info/RECORD
