Metadata-Version: 2.1
Name: lifecycle_ml_example
Version: 0.1.0
Summary: testing poetry
Author: Juan Camilo López Montes
Author-email: 143542016+juanlopez10pearls@users.noreply.github.com
Requires-Python: >=3.9,<4.0
Classifier: Programming Language :: Python :: 3
Classifier: Programming Language :: Python :: 3.9
Classifier: Programming Language :: Python :: 3.10
Classifier: Programming Language :: Python :: 3.11
Classifier: Programming Language :: Python :: 3.12
Requires-Dist: apache-airflow (==2.7.2)
Requires-Dist: apache-airflow-providers-docker (>=3.9.2,<4.0.0)
Requires-Dist: category-encoders (==2.6.3)
Requires-Dist: numpy (>=1.26.4,<2.0.0)
Requires-Dist: opentelemetry-proto (>=1.23.0,<2.0.0)
Requires-Dist: pandas (>=2.2.1,<3.0.0)
Requires-Dist: protobuf (>=3.19,<4.0)
Requires-Dist: pydantic (==1.10.12)
Requires-Dist: pyyaml (==6.0.1)
Requires-Dist: scikit-learn (>=1.4.1.post1,<2.0.0)
Requires-Dist: xgboost (>=2.0.3,<3.0.0)
